som.py
somde/__init__.py
somde/som.py
somde/util.py
somde-0.1.4.dist-info/LICENSE
somde-0.1.4.dist-info/METADATA
somde-0.1.4.dist-info/WHEEL
somde-0.1.4.dist-info/top_level.txt
somde-0.1.4.dist-info/RECORD
