Metadata-Version: 2.1
Name: somde
Version: 0.1.4
Summary: Algorithm for finding gene spatial pattern based on Gaussian process accelerated by SOM
Home-page: https://github.com/WhirlFirst/somde
Author: Minsheng Hao
Author-email: hmsh653@gmail.com
License: MIT
Keywords: spatial transcriptomics,SpatialDE,bioinformatics,self organizing map(SOM)
Platform: UNKNOWN
Requires-Dist: numpy (>=1.17.4)
Requires-Dist: pandas (>=0.25.3)
Requires-Dist: matplotlib (>=3.1.1)
Requires-Dist: somoclu (>=1.7.5)
Requires-Dist: SpatialDE (>=1.1.3)
Requires-Dist: patsy
